gavia/__init__.py
gavia/camera.py
gavia/camera_wip.py
gavia/gps.py
gavia/log.py
gavia/nav.py
gavia/time.py
gavia/tools.py
gavia/version.py
gavia/vizualise.py
gavia/image/__init__.py
gavia/image/io.py
gavia/image/warp.py
gavia-0.0.2.dist-info/LICENSE
gavia-0.0.2.dist-info/METADATA
gavia-0.0.2.dist-info/WHEEL
gavia-0.0.2.dist-info/top_level.txt
gavia-0.0.2.dist-info/RECORD
