Metadata-Version: 2.1
Name: gavia
Version: 0.0.2
Summary: Gavia is a Python package built for processing science data from the Gavia Autonomous Underwater Vehicle.
Home-page: http://github.com/brett-hosking/gavia
Author: brett hosking
Author-email: wilski@noc.ac.uk
License: MIT
Platform: UNKNOWN
Requires-Dist: numpy (>=1.16.2)
Requires-Dist: imageio (>=2.5.0)
Requires-Dist: matplotlib (>=3.0.3)
Requires-Dist: pandas (>=0.24.2)
